odoo/addons/odoo_instance/README.rst
odoo/addons/odoo_instance/__init__.py
odoo/addons/odoo_instance/__manifest__.py
odoo/addons/odoo_instance/data/calendar_tags.xml
odoo/addons/odoo_instance/data/ir_cron.xml
odoo/addons/odoo_instance/data/odoo12_core_modules_data.xml
odoo/addons/odoo_instance/data/odoo14_core_modules_app_data.xml
odoo/addons/odoo_instance/data/odoo_version_data.xml
odoo/addons/odoo_instance/features/behave.ini
odoo/addons/odoo_instance/features/environment.py
odoo/addons/odoo_instance/features/instance_management.feature
odoo/addons/odoo_instance/features/steps/instance_management_steps.py
odoo/addons/odoo_instance/models/__init__.py
odoo/addons/odoo_instance/models/calendar_event.py
odoo/addons/odoo_instance/models/import_requirements_wizard.py
odoo/addons/odoo_instance/models/odoo_instance.py
odoo/addons/odoo_instance/models/odoo_instance_database.py
odoo/addons/odoo_instance/models/odoo_instance_module.py
odoo/addons/odoo_instance/models/odoo_instance_process.py
odoo/addons/odoo_instance/models/odoo_instance_window.py
odoo/addons/odoo_instance/models/odoo_release.py
odoo/addons/odoo_instance/models/odoo_version.py
odoo/addons/odoo_instance/models/process_module_rel.py
odoo/addons/odoo_instance/models/project_project.py
odoo/addons/odoo_instance/models/res_partner.py
odoo/addons/odoo_instance/readme/DESCRIPTION.rst
odoo/addons/odoo_instance/readme/HISTORY.rst
odoo/addons/odoo_instance/security/__init__.py
odoo/addons/odoo_instance/security/ir.model.access.csv
odoo/addons/odoo_instance/security/security_groups.xml
odoo/addons/odoo_instance/static/description/index.html
odoo/addons/odoo_instance/static/src/css/project_instance.css
odoo/addons/odoo_instance/static/src/img/icon.png
odoo/addons/odoo_instance/static/src/js/project_instance.js
odoo/addons/odoo_instance/tests/__init__.py
odoo/addons/odoo_instance/tests/test_project_instance.py
odoo/addons/odoo_instance/views/import_requirements_wizard_view.xml
odoo_addon_odoo_instance-16.0.2.0.0.6.dist-info/METADATA
odoo_addon_odoo_instance-16.0.2.0.0.6.dist-info/WHEEL
odoo_addon_odoo_instance-16.0.2.0.0.6.dist-info/top_level.txt
odoo_addon_odoo_instance-16.0.2.0.0.6.dist-info/RECORD
