Metadata-Version: 2.4
Name: odoo-addon-odoo_instance
Version: 16.0.2.0.0.6
Summary: Manage Odoo instances with relevant information
Home-page: https://www.coopdevs.org
Author: Coopdevs
License: AGPL-3
Classifier: Programming Language :: Python
Classifier: Framework :: Odoo
Classifier: Framework :: Odoo :: 16.0
Classifier: License :: OSI Approved :: GNU Affero General Public License v3
Requires-Python: >=3.10
Requires-Dist: odoo-addon-contract<16.1dev,>=16.0dev
Requires-Dist: odoo-addon-queue_job<16.1dev,>=16.0dev
Requires-Dist: odoo<16.1dev,>=16.0a
Requires-Dist: pyyaml
Dynamic: author
Dynamic: classifier
Dynamic: description
Dynamic: home-page
Dynamic: license
Dynamic: requires-dist
Dynamic: requires-python
Dynamic: summary
